rocm_smi_exporter/__init__.py
rocm_smi_exporter/main.py
lamini_rocm_smi_exporter-0.0.1a5.dist-info/METADATA
lamini_rocm_smi_exporter-0.0.1a5.dist-info/WHEEL
lamini_rocm_smi_exporter-0.0.1a5.dist-info/entry_points.txt
lamini_rocm_smi_exporter-0.0.1a5.dist-info/top_level.txt
lamini_rocm_smi_exporter-0.0.1a5.dist-info/RECORD
