Metadata-Version: 2.1
Name: lamini-rocm-smi-exporter
Version: 0.0.1a5
Summary: Export rocm-smi metrics as prometheus metrics
Author-email: Yaxiong Zhao <yaxiong@powerml.co>
Maintainer-email: Yaxiong Zhao <yaxiong@powerml.co>
Requires-Python: >=3.10
Requires-Dist: prometheus-client ==0.20.0
Requires-Dist: pyrsmi ==1.0.1
